pyviewer/Hack-Regular.ttf
pyviewer/MPLUSRounded1c-Medium.ttf
pyviewer/__init__.py
pyviewer/_version.py
pyviewer/custom_ops.py
pyviewer/docking_viewer.py
pyviewer/easy_dict.py
pyviewer/gl_viewer.py
pyviewer/imgui_bundle_glfw3_backend.py
pyviewer/imgui_themes.py
pyviewer/params.py
pyviewer/raw_gl_docking_test.py
pyviewer/roboto_mono.ttf
pyviewer/single_image_viewer.py
pyviewer/toolbar_viewer.py
pyviewer/utils.py
pyviewer/custom_ops/cuda_gl_interop.cpp
pyviewer-2.0.2.dist-info/licenses/LICENSE
pyviewer-2.0.2.dist-info/METADATA
pyviewer-2.0.2.dist-info/WHEEL
pyviewer-2.0.2.dist-info/top_level.txt
pyviewer-2.0.2.dist-info/RECORD
