Metadata-Version: 2.4
Name: pyviewer
Version: 2.0.2
Summary: Interactyive python viewers
Home-page: https://github.com/harskish/pyviewer
Author: Erik Härkönen
Author-email: erik.harkonen@hotmail.com
License: CC BY-NC-SA 4.0
License-File: LICENSE
Requires-Dist: glfw==2.8.0
Requires-Dist: numpy
Requires-Dist: pyopengl==3.1.7
Requires-Dist: imgui-bundle==1.6.2
Requires-Dist: setuptools<=72.1.0
Requires-Dist: light-process==0.0.7
Requires-Dist: py==1.11.0
Requires-Dist: ninja
Dynamic: author
Dynamic: author-email
Dynamic: description
Dynamic: description-content-type
Dynamic: home-page
Dynamic: license
Dynamic: license-file
Dynamic: requires-dist
Dynamic: summary
